{
    "testament": {
        "0": ["ALsluAKBZ-c"],
        "1": ["Q0BrP8bqj0c"]
    },
    "section": {
        "0": ["5nvVVcYD-0w", "QpnIrbq2bKo"],
        "1": ["ZPZ2uABVMKA"],
        "2": ["CGbNw855ksw", "Z-17KxpjL0Q"],
        "3": ["RaucATa9ufQ"],
        "4": ["-G3epBHLc2E"],
        "5": ["GaAc8SCcFnk"],
        "6": ["RXV4vYBl7Wk"],
        "7": ["7e-z1R62FtI"]
    },
    "book": {
        "0": ["5nvVVcYD-0w", "QpnIrbq2bKo"],
        "1": ["6UoCmakZmys"],
        "2": ["l3QkE6nKylM"],
        "3": ["l3QkE6nKylM"],
        "4": ["l3QkE6nKylM"],
        "5": ["wWLv_ITyKYc"],
        "6": ["WhP7AZQlzCg"],
        "7": ["qn-hLHWwRYY"],
        "8": ["1fNWTZZwgbs"],
        "9": ["aW9Q3Jt6Yvk"],
        "10": ["PUEYCVXJM3k"],
        "11": ["urlvnxCaL00"],
        "12": ["7RoqnGcEjcs"],
        "13": ["kbPBDKOn1cc"],
        "14": ["No7Nq6IX23c"],
        "15": ["pXTXlDxQsvc"],
        "16": ["oE9qqW1-BkU"],
        "17": ["Y71r-T98E2Q"],
        "18": ["vmx4UjRFp0M"],
        "19": ["3lfPK2vfC54"],
        "20": ["yiHf8klCCc4"],
        "21": ["ej_6dVdJSIU", "0SVTl4Xa5fY"],
        "22": ["CGbNw855ksw", "Z-17KxpjL0Q"],
        "23": ["G-2e9mMf7E8","RUfh_wOsauk"],
        "24": ["XIb_dCIxzr0", "26z_KhwNdD8"],
        "25": ["HGHqu9-DtXk"],
        "26": ["3Dv4-n6OYGI", "GGCF3OPWN14"],
        "27": ["HPGShWZ4Jvk"],
        "28": ["_106IfO6Kc0"],
        "29": ["juPvv_xcX-U"],
        "30": ["oFZknKPNvz8"],
        "31": ["OPMaRqGJPUU"],
        "32": ["Y30DanA5EhU"],
        "33": ["MFEUEcylwLc"],
        "34": ["dLIabZc0O4c"],
        "35": ["i4ogCrEoG5s"],
        "36": ["mGgWaPGpGz4"],
        "37": ["zQLazbgz90c"],
        "38": ["kE6SZ1ogOVU"],
        "39": ["9cSC9uobtPM"],
        "40": ["R-CIPu1nko8", "SDeCWW_Bnyw"],
        "41": ["p8GDFPdaQZQ"],
        "42": ["RSK36cHbrk0"],
        "43": ["d0A6Uchb1F8", "_TzdEPuqgQg"],
        "44": ["4KC7xE4fgOw"],
        "45": ["lrsQ1tc-2wk"],
        "46": ["AzmYV8GNAIM"],
        "47": ["j9phNEaPrv8"],
        "48": ["j9phNEaPrv8"],
        "49": ["j9phNEaPrv8"],
        "50": ["j9phNEaPrv8"],
        "51": ["j9phNEaPrv8"],
        "52": ["xQwnH8th_fs"],
        "53": ["JydNSlufRIs"],
        "54": ["h6KM3S7sOjs"],
        "55": ["h6KM3S7sOjs"],
        "56": ["HR7xaHv3Ias"],
        "57": ["HR7xaHv3Ias"],
        "58": ["bVFW3wbi9pk"],
        "59": ["bVFW3wbi9pk"],
        "60": ["YvoWDXNDJgs"],
        "61": ["QJOju5Dw0V0"],
        "62": ["0h1eoBeR4Jk"],
        "63": ["kOYy8iCfIJ4"],
        "64": ["JqOqJlFF_eU"],
        "65": ["q5QEH9bH8AU"],
        "66": ["tp5MIrMZFqo"],
        "67": ["IJ-FekWUZzE"],
        "68": ["jH_aojNJM3E", "oNpTha80yyE"],
        "69": ["GQI72THyO5I", "F4isSyennFo"]
    }
}